ttk_text-0.2.2.dist-info/METADATA
ttk_text-0.2.2.dist-info/WHEEL
ttk_text-0.2.2.dist-info/entry_points.txt
ttk_text-0.2.2.dist-info/licenses/LICENSE
ttk_text/__init__.py
ttk_text/scrolled_text.py
ttk_text/utils.py
ttk_text-0.2.2.dist-info/RECORD
