Metadata-Version: 2.4
Name: ttk-text
Version: 0.2.2
Summary: Themed Tkinter Text widget with modern styling support.
Keywords: ttk,ttk-text,tkinter,tkinter-text,tk,tk-text
Author-Email: Jesse205 <jesse205@qq.com>
Maintainer-Email: Jesse205 <jesse205@qq.com>
License-Expression: MIT
Classifier: Programming Language :: Python :: 3
Classifier: Programming Language :: Python :: 3.9
Classifier: Programming Language :: Python :: 3.10
Classifier: Programming Language :: Python :: 3.11
Classifier: Programming Language :: Python :: 3.12
Classifier: Programming Language :: Python :: 3.13
Classifier: Programming Language :: Python :: Implementation :: CPython
Classifier: Operating System :: Microsoft :: Windows
Classifier: Operating System :: Microsoft :: Windows :: Windows 11
Classifier: Operating System :: Microsoft :: Windows :: Windows 10
Classifier: Operating System :: Microsoft :: Windows :: Windows 8.1
Classifier: Operating System :: Microsoft :: Windows :: Windows 8
Classifier: Operating System :: Microsoft :: Windows :: Windows 7
Classifier: Topic :: Software Development :: Libraries :: Python Modules
Project-URL: Repository, https://github.com/Jesse205/TtkText
Project-URL: Tracker, https://github.com/Jesse205/TtkText/issues
Project-URL: Changelog, https://github.com/Jesse205/TtkText/releases
Requires-Python: >=3.8
